pecanhq/__init__.py
pecanhq/meta.py
pecanhq/pecan.py
pecanhq/grant/__init__.py
pecanhq/grant/resources.py
pecanhq/grant/sdk.py
pecanhq-0.0.4.dist-info/METADATA
pecanhq-0.0.4.dist-info/WHEEL
pecanhq-0.0.4.dist-info/top_level.txt
pecanhq-0.0.4.dist-info/RECORD
