Metadata-Version: 2.1
Name: pecanhq
Version: 0.0.4
Summary: This client library unlocks Pecan IAM for server applications.
Home-page: UNKNOWN
License: UNKNOWN
Keywords: iam authorization authentication
Platform: UNKNOWN
Requires-Python: >=3.5,<4
Requires-Dist: requests
